jaypore_ci/__init__.py
jaypore_ci/__main__.py
jaypore_ci/changelog.py
jaypore_ci/clean.py
jaypore_ci/config.py
jaypore_ci/exceptions.py
jaypore_ci/executors/__init__.py
jaypore_ci/executors/docker.py
jaypore_ci/interfaces.py
jaypore_ci/jci.py
jaypore_ci/logging.py
jaypore_ci/remotes/__init__.py
jaypore_ci/remotes/email.py
jaypore_ci/remotes/git.py
jaypore_ci/remotes/gitea.py
jaypore_ci/remotes/github.py
jaypore_ci/remotes/mock.py
jaypore_ci/reporters/__init__.py
jaypore_ci/reporters/common.py
jaypore_ci/reporters/markdown.py
jaypore_ci/reporters/text.py
jaypore_ci/repos/__init__.py
jaypore_ci/repos/git.py
jaypore_ci-0.2.31.dist-info/WHEEL
jaypore_ci-0.2.31.dist-info/LICENSE
jaypore_ci-0.2.31.dist-info/METADATA
jaypore_ci-0.2.31.dist-info/RECORD
